qubu/__init__.py
qubu/_api.py
qubu/contract/__init__.py
qubu/contract/_comparison.py
qubu/contract/_evaluation.py
qubu/contract/_expression.py
qubu/contract/_geospatial.py
qubu/contract/_logical.py
qubu/drivers/__init__.py
qubu/drivers/mongodb/__init__.py
qubu/drivers/mongodb/_comparison.py
qubu/drivers/mongodb/_evaluation.py
qubu/drivers/mongodb/_expression.py
qubu/drivers/mongodb/_geospatial.py
qubu/drivers/mongodb/_logical.py
qubu-0.1.dist-info/LICENSE.md
qubu-0.1.dist-info/METADATA
qubu-0.1.dist-info/WHEEL
qubu-0.1.dist-info/top_level.txt
qubu-0.1.dist-info/RECORD
