Metadata-Version: 2.1
Name: qubu
Version: 0.1
Summary: A Simple Database Query Builder
Home-page: https://github.com/ashep/qubu
Author: Oleksandr Shepetko
Author-email: a@shepetko.com
License: UNKNOWN
Download-URL: https://github.com/ashep/qubu/archive/master.zip
Platform: UNKNOWN
Classifier: Development Status :: 5 - Production/Stable
Classifier: Intended Audience :: Developers
Classifier: License :: OSI Approved :: MIT License
Classifier: Operating System :: OS Independent
Classifier: Programming Language :: Python :: 3.6
Classifier: Programming Language :: Python :: 3.7
Classifier: Programming Language :: Python :: 3.8
Classifier: Topic :: Database
Classifier: Topic :: Software Development :: Code Generators
Classifier: Topic :: Software Development :: Libraries :: Python Modules
Requires-Dist: dicmer
